strawberry_openapi-0.2.1.dist-info/METADATA
strawberry_openapi-0.2.1.dist-info/WHEEL
strawberry_openapi/__init__.py
strawberry_openapi/_graph_response.py
strawberry_openapi/_openapi.py
strawberry_openapi/_operation.py
strawberry_openapi/_operation_factory.py
strawberry_openapi/_path.py
strawberry_openapi/django/__init__.py
strawberry_openapi/py.typed
strawberry_openapi-0.2.1.dist-info/RECORD
