Metadata-Version: 2.1
Name: strawberry-openapi
Version: 0.2.1
Summary: Easily convert your Strawberry GraphQL schema to OpenAPI
Author-Email: Patrick Arminio <patrick.arminio@gmail.com>
License: MIT
Requires-Python: >=3.8
Requires-Dist: strawberry-graphql>=0.215.0
Requires-Dist: pydantic>=2.5.1
Requires-Dist: typing-extensions>=4.8.0
Requires-Dist: pytest-django>=4.7.0
Requires-Dist: pytest-snapshot>=0.9.0
